README
setup.cfg
setup.py
oyoyo/__init__.py
oyoyo/client.py
oyoyo/cmdhandler.py
oyoyo/examplebot.py
oyoyo/helpers.py
oyoyo/ircevents.py
oyoyo/parse.py
oyoyo.egg-info/PKG-INFO
oyoyo.egg-info/SOURCES.txt
oyoyo.egg-info/dependency_links.txt
oyoyo.egg-info/entry_points.txt
oyoyo.egg-info/top_level.txt