Metadata-Version: 1.0
Name: oyoyo
Version: 0.0.0dev
Summary: a fast, simple irc module suitable for clients, bots and games
Home-page: http://code.google.com/p/oyoyo/
Author: Dunk Fordyce, Daniel da Silva (current)
Author-email: dunkfordyce@gmail.com, meltingwax@gmail.com
License: MIT
Platform: UNKNOWN
